{
  "definition": {
    "word": "頷く",
    "reading": "うなずく",
    "romaji": "unazuku",
    "jlpt": "N2",
    "frequency": 5000,
    "entries": [
      {
        "pos": [
          "Godan verb with 'ku' ending",
          "intransitive verb"
        ],
        "meanings": [
          "to nod",
          "to bow one's head in assent",
          "to agree"
        ]
      }
    ]
  },
  "related": [],
  "idioms": [],
  "lessons": [
    {
      "japanese": "うなずくことは承知の合図だ。",
      "reading": null,
      "english": "A nod is a sign of agreement.",
      "lessonInfo": {
        "level": "intermediate"
      }
    },
    {
      "japanese": "うなずくことは承知の合図だ。",
      "reading": null,
      "english": "A nod is a sign of agreement.",
      "lessonInfo": {
        "level": "intermediate"
      }
    },
    {
      "japanese": "当然だな、といった顔つきでうなずく。",
      "reading": null,
      "english": "He nods as if to say \"of course\".",
      "lessonInfo": {
        "level": "intermediate"
      }
    },
    {
      "japanese": "当然だな、といった顔つきでうなずく。",
      "reading": null,
      "english": "He nods as if to say \"of course\".",
      "lessonInfo": {
        "level": "intermediate"
      }
    }
  ]
}