{
  "definition": {
    "word": "お袋",
    "reading": "おふくろ",
    "romaji": "ofukuro",
    "jlpt": "N1",
    "frequency": 5000,
    "entries": [
      {
        "pos": [
          "noun (common) (futsuumeishi)"
        ],
        "meanings": [
          "(one's) mother"
        ]
      }
    ]
  },
  "related": [
    {
      "word": "袋",
      "reading": "ふくろ",
      "meaning": "bag"
    },
    {
      "word": "手袋",
      "reading": "てぶくろ",
      "meaning": "glove"
    },
    {
      "word": "足袋",
      "reading": "たび",
      "meaning": "tabi"
    }
  ],
  "idioms": [],
  "lessons": [
    {
      "japanese": "一人暮らしをしていると、お袋の味が恋しくなるよ。",
      "reading": null,
      "english": "Living on my own, I really miss my mom's cooking.",
      "lessonInfo": {
        "level": "upper-intermediate"
      }
    },
    {
      "japanese": "お袋の前ではそのことに触れるな。",
      "reading": null,
      "english": "Don't talk about it in my mother's presence.",
      "lessonInfo": {
        "level": "upper-intermediate"
      }
    },
    {
      "japanese": "一人暮らしをしていると、お袋の味が恋しくなるよ。",
      "reading": null,
      "english": "Living on my own, I really miss my mom's cooking.",
      "lessonInfo": {
        "level": "upper-intermediate"
      }
    },
    {
      "japanese": "お袋の前ではそのことに触れるな。",
      "reading": null,
      "english": "Don't talk about it in my mother's presence.",
      "lessonInfo": {
        "level": "upper-intermediate"
      }
    }
  ]
}