{
  "definition": {
    "word": "況して",
    "reading": "まして",
    "romaji": "mashite",
    "jlpt": "N1",
    "frequency": 5000,
    "entries": [
      {
        "pos": [
          "expressions (phrases, clauses, etc.)",
          "adverb (fukushi)"
        ],
        "meanings": [
          "still more",
          "to say nothing of",
          "not to mention"
        ]
      },
      {
        "pos": [
          "expressions (phrases, clauses, etc.)",
          "adverb (fukushi)"
        ],
        "meanings": [
          "still less"
        ]
      }
    ]
  },
  "related": [
    {
      "word": "好況",
      "reading": "こうきょう",
      "meaning": "prosperous (economic) conditions"
    },
    {
      "word": "不況",
      "reading": "ふきょう",
      "meaning": "(economic) depression"
    }
  ],
  "idioms": [],
  "lessons": [
    {
      "japanese": "「手伝ってくれてありがとう」「どういたしまして」",
      "reading": null,
      "english": "\"Thank you for helping me.\" \"Don't mention it.\"",
      "lessonInfo": {
        "level": "intermediate"
      }
    },
    {
      "japanese": "「ありがとう」「どういたしまして」",
      "reading": null,
      "english": "\"Thank you.\" \"You're welcome.\"",
      "lessonInfo": {
        "level": "elementary"
      }
    },
    {
      "japanese": "「ありがとうご座います」「どう致しまして」",
      "reading": null,
      "english": "\"Thank you.\" \"You're welcome.\"",
      "lessonInfo": {
        "level": "intermediate"
      }
    },
    {
      "japanese": "「ありがとうございます」「どういたしまして」",
      "reading": null,
      "english": "\"Thank you.\" \"You're welcome.\"",
      "lessonInfo": {
        "level": "elementary"
      }
    },
    {
      "japanese": "「ありがとうございました」「どういたしまして」",
      "reading": null,
      "english": "\"Thank you.\" \"You're welcome.\"",
      "lessonInfo": {
        "level": "elementary"
      }
    },
    {
      "japanese": "これにつきまして、お考えをお聞かせ願えればと存じます。",
      "reading": null,
      "english": "I look forward to hearing your thoughts on this matter.",
      "lessonInfo": {
        "level": "upper-intermediate"
      }
    },
    {
      "japanese": "「手伝ってくれてありがとう」「どういたしまして」",
      "reading": null,
      "english": "\"Thank you for helping me.\" \"Don't mention it.\"",
      "lessonInfo": {
        "level": "intermediate"
      }
    },
    {
      "japanese": "「手伝ってくれてありがとう」「どういたしまして」",
      "reading": null,
      "english": "\"Thank you for your help.\" \"It's my pleasure.\"",
      "lessonInfo": {
        "level": "intermediate"
      }
    },
    {
      "japanese": "「手伝ってくれてありがとう」「どういたしまして」",
      "reading": null,
      "english": "\"Thanks for the help.\" \"Don't mention it.\"",
      "lessonInfo": {
        "level": "intermediate"
      }
    },
    {
      "japanese": "「手伝ってくれてありがとう」「どういたしまして」",
      "reading": null,
      "english": "\"Thank you for your help.\" \"You're welcome.\"",
      "lessonInfo": {
        "level": "intermediate"
      }
    },
    {
      "japanese": "「ありがとう」「どういたしまして」",
      "reading": null,
      "english": "\"Thank you.\" \"You're welcome.\"",
      "lessonInfo": {
        "level": "elementary"
      }
    },
    {
      "japanese": "「ありがとう」「どういたしまして」",
      "reading": null,
      "english": "\"Thanks.\" \"You're welcome.\"",
      "lessonInfo": {
        "level": "elementary"
      }
    },
    {
      "japanese": "「ありがとう」「どういたしまして」",
      "reading": null,
      "english": "\"Thanks.\" \"My pleasure.\"",
      "lessonInfo": {
        "level": "elementary"
      }
    },
    {
      "japanese": "これにつきまして、お考えをお聞かせ願えればと存じます。",
      "reading": null,
      "english": "I look forward to hearing your thoughts on this matter.",
      "lessonInfo": {
        "level": "upper-intermediate"
      }
    },
    {
      "japanese": "教授は私の研究を励ましてくれた。",
      "reading": null,
      "english": "The professor encouraged me in my studies.",
      "lessonInfo": {
        "level": "upper-intermediate"
      }
    }
  ]
}