{
  "definition": {
    "word": "パパ",
    "reading": "パパ",
    "romaji": "papa",
    "jlpt": "N4",
    "frequency": 5000,
    "entries": [
      {
        "pos": [
          "noun (common) (futsuumeishi)"
        ],
        "meanings": [
          "dad",
          "daddy",
          "papa"
        ]
      },
      {
        "pos": [
          "noun (common) (futsuumeishi)"
        ],
        "meanings": [
          "sugar daddy"
        ]
      }
    ]
  },
  "related": [],
  "idioms": [],
  "lessons": [
    {
      "japanese": "ママもパパもひどくいらだっているの。",
      "reading": null,
      "english": "Mummy and Daddy are very nervous.",
      "lessonInfo": {
        "level": "elementary"
      }
    },
    {
      "japanese": "パパにつかまれ！",
      "reading": null,
      "english": "Hang onto Daddy!",
      "lessonInfo": {
        "level": "newbie"
      }
    },
    {
      "japanese": "パパに言いつけますよ。",
      "reading": null,
      "english": "I'll tell Daddy on you.",
      "lessonInfo": {
        "level": "elementary"
      }
    },
    {
      "japanese": "パパがおならをした。",
      "reading": null,
      "english": "Daddy passed gas.",
      "lessonInfo": {
        "level": "newbie"
      }
    },
    {
      "japanese": "パパどこに行くの？",
      "reading": null,
      "english": "Where are you going, Dad?",
      "lessonInfo": {
        "level": "newbie"
      }
    }
  ]
}