{
  "definition": {
    "word": "判決",
    "reading": "はんけつ",
    "romaji": "hanketsu",
    "jlpt": "N1",
    "frequency": 250,
    "entries": [
      {
        "pos": [
          "noun (common) (futsuumeishi)",
          "noun or participle which takes the aux. verb suru",
          "transitive verb"
        ],
        "meanings": [
          "judicial decision",
          "judgement",
          "judgment",
          "sentence",
          "decree"
        ]
      }
    ]
  },
  "related": [
    {
      "word": "決議",
      "reading": "けつぎ",
      "meaning": "resolution"
    },
    {
      "word": "決算",
      "reading": "けっさん",
      "meaning": "settlement of accounts"
    },
    {
      "word": "決勝",
      "reading": "けっしょう",
      "meaning": "decision of a contest"
    },
    {
      "word": "決意",
      "reading": "けつい",
      "meaning": "decision"
    },
    {
      "word": "決断",
      "reading": "けつだん",
      "meaning": "decision"
    },
    {
      "word": "採決",
      "reading": "さいけつ",
      "meaning": "vote"
    },
    {
      "word": "対決",
      "reading": "たいけつ",
      "meaning": "confrontation"
    },
    {
      "word": "判定",
      "reading": "はんてい",
      "meaning": "judgement"
    },
    {
      "word": "議決",
      "reading": "ぎけつ",
      "meaning": "resolution"
    },
    {
      "word": "否決",
      "reading": "ひけつ",
      "meaning": "rejection"
    },
    {
      "word": "決",
      "reading": "けつ",
      "meaning": "decision"
    },
    {
      "word": "多数決",
      "reading": "たすうけつ",
      "meaning": "majority decision"
    },
    {
      "word": "裁判",
      "reading": "さいばん",
      "meaning": "trial"
    },
    {
      "word": "判断",
      "reading": "はんだん",
      "meaning": "judgment"
    },
    {
      "word": "批判",
      "reading": "ひはん",
      "meaning": "criticism"
    },
    {
      "word": "解決",
      "reading": "かいけつ",
      "meaning": "settlement"
    },
    {
      "word": "決定",
      "reading": "けってい",
      "meaning": "decision"
    }
  ],
  "idioms": [],
  "lessons": [
    {
      "japanese": "殺人犯は有罪判決を受けて終身刑に処せられた。",
      "reading": null,
      "english": "The murderer was convicted and sentenced to life in prison.",
      "lessonInfo": {
        "level": "upper-intermediate"
      }
    },
    {
      "japanese": "殺人犯は有罪判決を受けて終身刑に処せられた。",
      "reading": null,
      "english": "The murderer was convicted and sentenced to life in prison.",
      "lessonInfo": {
        "level": "upper-intermediate"
      }
    },
    {
      "japanese": "伊藤太郎は有罪と判決された。",
      "reading": null,
      "english": "Taro Ito was found guilty.",
      "lessonInfo": {
        "level": "upper-intermediate"
      }
    },
    {
      "japanese": "まだ誰もその犯罪で有罪判決を受けていない。",
      "reading": null,
      "english": "No one has been convicted of the crime yet.",
      "lessonInfo": {
        "level": "upper-intermediate"
      }
    },
    {
      "japanese": "ついに、その残酷な男に刑務所行きの判決がくだされた。",
      "reading": null,
      "english": "Eventually the cruel man was sentenced to jail.",
      "lessonInfo": {
        "level": "upper-intermediate"
      }
    },
    {
      "japanese": "その判決が不満で上告する。",
      "reading": null,
      "english": "I will appeal against the sentence.",
      "lessonInfo": {
        "level": "intermediate"
      }
    },
    {
      "japanese": "その男は、終身刑であると裁判官が判決を下した時、取り乱した。",
      "reading": null,
      "english": "The man went to pieces when the judge said he would have to go to prison for life.",
      "lessonInfo": {
        "level": "upper-intermediate"
      }
    },
    {
      "japanese": "その裁判官は、最終判決をひるがえした。",
      "reading": null,
      "english": "The judge reversed the final decision.",
      "lessonInfo": {
        "level": "upper-intermediate"
      }
    },
    {
      "japanese": "法廷は彼に有罪の判決を下した。",
      "reading": null,
      "english": "The court judged him guilty.",
      "lessonInfo": {
        "level": "upper-intermediate"
      }
    },
    {
      "japanese": "法廷は遺言状が有効であるとの判決を下した。",
      "reading": null,
      "english": "The court adjudged that the will was valid.",
      "lessonInfo": {
        "level": "upper-intermediate"
      }
    },
    {
      "japanese": "法廷はその訴訟に判決を下した。",
      "reading": null,
      "english": "The court judged the case.",
      "lessonInfo": {
        "level": "upper-intermediate"
      }
    },
    {
      "japanese": "法廷では彼を有罪と判決した。",
      "reading": null,
      "english": "The court found him guilty.",
      "lessonInfo": {
        "level": "upper-intermediate"
      }
    },
    {
      "japanese": "被告は判決に不服でためらわずに控訴した。",
      "reading": null,
      "english": "The defendant appealed against the sentence without hesitation.",
      "lessonInfo": {
        "level": "upper-intermediate"
      }
    },
    {
      "japanese": "被告は死刑判決を受けた。",
      "reading": null,
      "english": "The defendant was sentenced to death.",
      "lessonInfo": {
        "level": "upper-intermediate"
      }
    }
  ]
}