{
  "definition": {
    "word": "変動",
    "reading": "へんどう",
    "romaji": "hendou",
    "jlpt": "N1",
    "frequency": 1750,
    "entries": [
      {
        "pos": [
          "noun (common) (futsuumeishi)",
          "noun or participle which takes the aux. verb suru",
          "intransitive verb"
        ],
        "meanings": [
          "change",
          "fluctuation"
        ]
      }
    ]
  },
  "related": [
    {
      "word": "動き",
      "reading": "うごき",
      "meaning": "movement"
    },
    {
      "word": "不動産",
      "reading": "ふどうさん",
      "meaning": "real estate"
    },
    {
      "word": "動向",
      "reading": "どうこう",
      "meaning": "trend"
    },
    {
      "word": "変革",
      "reading": "へんかく",
      "meaning": "change"
    },
    {
      "word": "動機",
      "reading": "どうき",
      "meaning": "motive"
    },
    {
      "word": "騒動",
      "reading": "そうどう",
      "meaning": "riot"
    },
    {
      "word": "暴動",
      "reading": "ぼうどう",
      "meaning": "insurrection"
    },
    {
      "word": "一変",
      "reading": "いっぺん",
      "meaning": "complete change"
    },
    {
      "word": "出動",
      "reading": "しゅつどう",
      "meaning": "mobilization"
    },
    {
      "word": "動員",
      "reading": "どういん",
      "meaning": "mobilization"
    },
    {
      "word": "振動",
      "reading": "しんどう",
      "meaning": "oscillation"
    },
    {
      "word": "変遷",
      "reading": "へんせん",
      "meaning": "change"
    },
    {
      "word": "動力",
      "reading": "どうりょく",
      "meaning": "power"
    },
    {
      "word": "変化",
      "reading": "へんか",
      "meaning": "change"
    },
    {
      "word": "運動",
      "reading": "うんどう",
      "meaning": "exercise"
    },
    {
      "word": "行動",
      "reading": "こうどう",
      "meaning": "action"
    },
    {
      "word": "自動車",
      "reading": "じどうしゃ",
      "meaning": "car"
    },
    {
      "word": "大変",
      "reading": "たいへん",
      "meaning": "very"
    },
    {
      "word": "動物",
      "reading": "どうぶつ",
      "meaning": "animal"
    },
    {
      "word": "変わる",
      "reading": "かわる",
      "meaning": "to change"
    }
  ],
  "idioms": [],
  "lessons": [
    {
      "japanese": "金の価格は日ごとに変動する。",
      "reading": null,
      "english": "The price of gold fluctuates daily.",
      "lessonInfo": {
        "level": "intermediate"
      }
    },
    {
      "japanese": "金の価格は毎日変動します。",
      "reading": null,
      "english": "The price of gold fluctuates daily.",
      "lessonInfo": {
        "level": "intermediate"
      }
    },
    {
      "japanese": "この国では年間を通じて気温の変動がほとんどない。",
      "reading": null,
      "english": "This country has an even temperature throughout the year.",
      "lessonInfo": {
        "level": "intermediate"
      }
    },
    {
      "japanese": "世界が一丸となって気候変動の問題に取り組む必要がある。",
      "reading": null,
      "english": "The whole world needs to tackle the problem of climate change together.",
      "lessonInfo": {
        "level": "upper-intermediate"
      }
    },
    {
      "japanese": "年金の額は原則として前年の物価変動にスライドして算出される。",
      "reading": null,
      "english": "As a general rule, the pension amount is based on price changes in the previous year.",
      "lessonInfo": {
        "level": "upper-intermediate"
      }
    },
    {
      "japanese": "炭素排出量の変動が、以下のグラフに描かれている。",
      "reading": null,
      "english": "The differing volumes of carbon emissions are plotted in the graph below.",
      "lessonInfo": {
        "level": "upper-intermediate"
      }
    },
    {
      "japanese": "世界貿易の変動パターンが次の表で明らかにされている。",
      "reading": null,
      "english": "The shifting pattern of world trade is made clear in the following table.",
      "lessonInfo": {
        "level": "upper-intermediate"
      }
    },
    {
      "japanese": "人口は変動しないでいる。",
      "reading": null,
      "english": "The population remains stationary.",
      "lessonInfo": {
        "level": "intermediate"
      }
    },
    {
      "japanese": "消費者物価指数は激しく変動しています。",
      "reading": null,
      "english": "The consumer price index has been fluctuating wildly.",
      "lessonInfo": {
        "level": "upper-intermediate"
      }
    },
    {
      "japanese": "金の価格は日ごとに変動する。",
      "reading": null,
      "english": "The price of gold fluctuates daily.",
      "lessonInfo": {
        "level": "intermediate"
      }
    },
    {
      "japanese": "この国では年間を通じて気温の変動がほとんどない。",
      "reading": null,
      "english": "This country has an even temperature throughout the year.",
      "lessonInfo": {
        "level": "intermediate"
      }
    },
    {
      "japanese": "消費者物価指数は激しく変動しています。",
      "reading": null,
      "english": "The consumer price index has been fluctuating wildly.",
      "lessonInfo": {
        "level": "upper-intermediate"
      }
    },
    {
      "japanese": "人口は変動しないでいる。",
      "reading": null,
      "english": "The population remains stationary.",
      "lessonInfo": {
        "level": "intermediate"
      }
    }
  ]
}