{
  "definition": {
    "word": "必ずしも",
    "reading": "かならずしも",
    "romaji": "kanarazushimo",
    "jlpt": "N3",
    "frequency": 2250,
    "entries": [
      {
        "pos": [
          "adverb (fukushi)"
        ],
        "meanings": [
          "(not) always",
          "(not) necessarily",
          "(not) entirely",
          "(not) all"
        ]
      }
    ]
  },
  "related": [
    {
      "word": "必ず",
      "reading": "かならず",
      "meaning": "always"
    },
    {
      "word": "必死",
      "reading": "ひっし",
      "meaning": "frantic"
    },
    {
      "word": "必要",
      "reading": "ひつよう",
      "meaning": "necessary"
    },
    {
      "word": "必需品",
      "reading": "ひつじゅひん",
      "meaning": "necessities"
    }
  ],
  "idioms": [],
  "lessons": [
    {
      "japanese": "必ずしも行く必要はないよ。",
      "reading": null,
      "english": "You do not necessarily have to go there yourself.",
      "lessonInfo": {
        "level": "intermediate"
      }
    },
    {
      "japanese": "金持ちは必ずしも幸せではない。",
      "reading": null,
      "english": "The rich are not always happy.",
      "lessonInfo": {
        "level": "intermediate"
      }
    },
    {
      "japanese": "光るもの必ずしも金ならず。",
      "reading": null,
      "english": "All that glitters is not gold.",
      "lessonInfo": {
        "level": "intermediate"
      }
    }
  ]
}