{
  "definition": {
    "word": "忘れる",
    "reading": "わすれる",
    "romaji": "wasureru",
    "jlpt": "N5",
    "frequency": 5000,
    "entries": [
      {
        "pos": [
          "Ichidan verb",
          "transitive verb"
        ],
        "meanings": [
          "to forget",
          "to leave carelessly",
          "to be forgetful of",
          "to forget about",
          "to forget (an article)"
        ]
      }
    ]
  },
  "related": [],
  "idioms": [
    {
      "word": "喉元過ぎれば熱さを忘れる",
      "reading": "のどもとすぎればあつさをわすれる",
      "meaning": "danger past and God forgotten",
      "type": "proverb"
    }
  ],
  "lessons": []
}