{
  "definition": {
    "word": "暖かい",
    "reading": "あたたかい",
    "romaji": "atatakai",
    "jlpt": "N5",
    "frequency": 10250,
    "entries": [
      {
        "pos": [
          "adjective (keiyoushi)"
        ],
        "meanings": [
          "warm",
          "mild",
          "(pleasantly) hot"
        ]
      },
      {
        "pos": [
          "adjective (keiyoushi)"
        ],
        "meanings": [
          "considerate",
          "kind",
          "genial"
        ]
      },
      {
        "pos": [
          "adjective (keiyoushi)"
        ],
        "meanings": [
          "warm (of a colour)",
          "mellow"
        ]
      },
      {
        "pos": [
          "adjective (keiyoushi)"
        ],
        "meanings": [
          "having enough money"
        ]
      }
    ]
  },
  "related": [],
  "idioms": [],
  "lessons": []
}