{
  "definition": {
    "word": "貧困",
    "reading": "ひんこん",
    "romaji": "hinkon",
    "jlpt": "N1",
    "frequency": 3250,
    "entries": [
      {
        "pos": [
          "noun (common) (futsuumeishi)",
          "adjectival nouns or quasi-adjectives (keiyodoshi)",
          "nouns which may take the genitive case particle 'no'"
        ],
        "meanings": [
          "poverty",
          "penury",
          "need",
          "destitution"
        ]
      },
      {
        "pos": [
          "noun (common) (futsuumeishi)",
          "adjectival nouns or quasi-adjectives (keiyodoshi)",
          "nouns which may take the genitive case particle 'no'"
        ],
        "meanings": [
          "shortage",
          "lack",
          "want"
        ]
      }
    ]
  },
  "related": [
    {
      "word": "貧乏",
      "reading": "びんぼう",
      "meaning": "poverty-stricken"
    },
    {
      "word": "貧弱",
      "reading": "ひんじゃく",
      "meaning": "poor"
    },
    {
      "word": "困難",
      "reading": "こんなん",
      "meaning": "difficulty"
    }
  ],
  "idioms": [],
  "lessons": [
    {
      "japanese": "ライ麦は貧困の穀物と称されていた。",
      "reading": null,
      "english": "Rye was called the grain of poverty.",
      "lessonInfo": {
        "level": "upper-intermediate"
      }
    },
    {
      "japanese": "ライ麦は貧困の穀物と称されていた。",
      "reading": null,
      "english": "Rye was called the grain of poverty.",
      "lessonInfo": {
        "level": "upper-intermediate"
      }
    },
    {
      "japanese": "我々は貧困のない生活が欲しい。",
      "reading": null,
      "english": "We want freedom from poverty.",
      "lessonInfo": {
        "level": "intermediate"
      }
    },
    {
      "japanese": "何人ぐらいの人々が、現在、貧困の中で生活しているのか。",
      "reading": null,
      "english": "How many people are now living in poverty?",
      "lessonInfo": {
        "level": "upper-intermediate"
      }
    },
    {
      "japanese": "音楽家が死んで遺族は貧困にさらされた。",
      "reading": null,
      "english": "The musician left his family poor.",
      "lessonInfo": {
        "level": "upper-intermediate"
      }
    },
    {
      "japanese": "貧困者が乞食をしていた。",
      "reading": null,
      "english": "The pauper was begging for a living.",
      "lessonInfo": {
        "level": "intermediate"
      }
    },
    {
      "japanese": "少数民族は偏見、貧困、抑圧と戦っている。",
      "reading": null,
      "english": "Ethnic minorities struggle against prejudice, poverty, and oppression.",
      "lessonInfo": {
        "level": "upper-intermediate"
      }
    },
    {
      "japanese": "貧困は幸福への障害とはならない。",
      "reading": null,
      "english": "Poverty is not a bar to happiness.",
      "lessonInfo": {
        "level": "upper-intermediate"
      }
    },
    {
      "japanese": "貧困は勤勉の母。",
      "reading": null,
      "english": "Want is the mother of industry.",
      "lessonInfo": {
        "level": "intermediate"
      }
    },
    {
      "japanese": "貧困は家庭を破壊するよりはむしろ団結せしめる。",
      "reading": null,
      "english": "Poverty keeps together more homes than it breaks up.",
      "lessonInfo": {
        "level": "upper-intermediate"
      }
    },
    {
      "japanese": "貧困は依然として犯罪の大きな原因である。",
      "reading": null,
      "english": "Poverty is still the major cause of crime.",
      "lessonInfo": {
        "level": "upper-intermediate"
      }
    },
    {
      "japanese": "貧困は依然として犯罪の主要原因である。",
      "reading": null,
      "english": "Poverty is still the major cause of crime.",
      "lessonInfo": {
        "level": "upper-intermediate"
      }
    }
  ]
}