{
  "definition": {
    "word": "蹴る",
    "reading": "ける",
    "romaji": "keru",
    "jlpt": "N3",
    "frequency": 5000,
    "entries": [
      {
        "pos": [
          "Godan verb with 'ru' ending",
          "transitive verb"
        ],
        "meanings": [
          "to kick"
        ]
      },
      {
        "pos": [
          "Godan verb with 'ru' ending",
          "transitive verb"
        ],
        "meanings": [
          "to refuse",
          "to reject"
        ]
      },
      {
        "pos": [
          "Godan verb with 'ru' ending",
          "transitive verb"
        ],
        "meanings": [
          "to stamp (on the ground)",
          "to firmly press one's feet (against something)"
        ]
      }
    ]
  },
  "related": [],
  "idioms": [],
  "lessons": []
}