{
  "definition": {
    "word": "アルバム",
    "reading": "アルバム",
    "romaji": "arubamu",
    "jlpt": "N3",
    "frequency": 5000,
    "entries": [
      {
        "pos": [
          "noun (common) (futsuumeishi)"
        ],
        "meanings": [
          "album"
        ]
      }
    ]
  },
  "related": [],
  "idioms": [],
  "lessons": [
    {
      "japanese": "そのアルバムは次の７月までには完成されているだろう。",
      "reading": null,
      "indonesian": "The album will have been completed by next July.",
      "lessonInfo": {
        "level": "intermediate"
      }
    },
    {
      "japanese": "スティービー・ワンダーのニューアルバムはありますか。",
      "reading": null,
      "indonesian": "Do you have Stevie Wonder's new album?",
      "lessonInfo": {
        "level": "elementary"
      }
    },
    {
      "japanese": "このアルバムを見るといつも高校時代を思い出す。",
      "reading": null,
      "indonesian": "I never see this album without thinking of my high school days.",
      "lessonInfo": {
        "level": "intermediate"
      }
    },
    {
      "japanese": "アルバムを見せてくれませんか。",
      "reading": null,
      "indonesian": "Will you show me your photo album?",
      "lessonInfo": {
        "level": "elementary"
      }
    },
    {
      "japanese": "あなたのアルバムを見せてくれる？",
      "reading": null,
      "indonesian": "Will you show me your album?",
      "lessonInfo": {
        "level": "elementary"
      }
    }
  ]
}