{
  "definition": {
    "word": "体温",
    "reading": "たいおん",
    "romaji": "taion",
    "jlpt": "N3",
    "frequency": 6750,
    "entries": [
      {
        "pos": [
          "noun (common) (futsuumeishi)"
        ],
        "meanings": [
          "suhu (tubuh)"
        ]
      }
    ]
  },
  "related": [
    {
      "word": "身体",
      "reading": "しんたい",
      "meaning": "tubuh"
    },
    {
      "word": "重体",
      "reading": "じゅうたい",
      "meaning": "sakit parah, kondisi kritis"
    },
    {
      "word": "正体",
      "reading": "しょうたい",
      "meaning": "bentuk alami, warna asli seseorang, karakter sejati"
    },
    {
      "word": "全体",
      "reading": "ぜんたい",
      "meaning": "keseluruhan, seluruh bagian, apa pun (masalahnya)"
    },
    {
      "word": "団体",
      "reading": "だんたい",
      "meaning": "organisasi, asosiasi"
    },
    {
      "word": "具体",
      "reading": "ぐたい",
      "meaning": "konkret, nyata, material"
    },
    {
      "word": "体育",
      "reading": "たいいく",
      "meaning": "pendidikan jasmani, senam, atletik"
    },
    {
      "word": "一体",
      "reading": "いったい",
      "meaning": "satu objek; tubuh; apa-apaan ini?; secara umum"
    },
    {
      "word": "体重",
      "reading": "たいじゅう",
      "meaning": "berat badan"
    },
    {
      "word": "気温",
      "reading": "きおん",
      "meaning": "suhu (cuaca - tidak digunakan untuk benda)"
    },
    {
      "word": "温暖",
      "reading": "おんだん",
      "meaning": "kehangatan"
    },
    {
      "word": "温度",
      "reading": "おんど",
      "meaning": "suhu"
    },
    {
      "word": "気体",
      "reading": "きたい",
      "meaning": "uap, gas"
    },
    {
      "word": "字体",
      "reading": "じたい",
      "meaning": "font, huruf"
    },
    {
      "word": "形態",
      "reading": "けいたい",
      "meaning": "bentuk, rupa, figur"
    }
  ],
  "idioms": [],
  "lessons": [
    {
      "japanese": "まず体温を計りましょう。",
      "reading": null,
      "indonesian": "Let's take your temperature first.",
      "lessonInfo": {
        "level": "intermediate"
      }
    },
    {
      "japanese": "さあ、体温を計りましょう。",
      "reading": null,
      "indonesian": "Now, I'll take your temperature.",
      "lessonInfo": {
        "level": "intermediate"
      }
    },
    {
      "japanese": "さあ、あなたの体温を計りましょう。",
      "reading": null,
      "indonesian": "Now, I'll take your temperature.",
      "lessonInfo": {
        "level": "intermediate"
      }
    }
  ]
}