{
  "definition": {
    "word": "国民",
    "reading": "こくみん",
    "romaji": "kokumin",
    "jlpt": "N3",
    "frequency": 250,
    "entries": [
      {
        "pos": [
          "noun (common) (futsuumeishi)"
        ],
        "meanings": [
          "nasional",
          "rakyat",
          "warga negara"
        ]
      },
      {
        "pos": [
          "noun (common) (futsuumeishi)"
        ],
        "meanings": [
          "Democratic Party for the People"
        ]
      }
    ]
  },
  "related": [
    {
      "word": "国家",
      "reading": "こっか",
      "meaning": "negara bagian, negara, bangsa"
    },
    {
      "word": "国会",
      "reading": "こっかい",
      "meaning": "Parlemen nasional, parlemen, kongres"
    },
    {
      "word": "全国",
      "reading": "ぜんこく",
      "meaning": "seluruh bangsa, di seluruh negeri, di seluruh negara"
    },
    {
      "word": "住民",
      "reading": "じゅうみん",
      "meaning": "penduduk, warga"
    },
    {
      "word": "国境",
      "reading": "こっきょう",
      "meaning": "perbatasan nasional atau negara bagian"
    },
    {
      "word": "国籍",
      "reading": "こくせき",
      "meaning": "kebangsaan"
    },
    {
      "word": "農民",
      "reading": "のうみん",
      "meaning": "petani, buruh tani"
    },
    {
      "word": "国語",
      "reading": "こくご",
      "meaning": "bahasa nasional"
    },
    {
      "word": "外国",
      "reading": "がいこく",
      "meaning": "negara asing; luar negeri"
    },
    {
      "word": "外国人",
      "reading": "がいこくじん",
      "meaning": "orang asing"
    },
    {
      "word": "国",
      "reading": "くに",
      "meaning": "negara; tempat asal"
    },
    {
      "word": "市民",
      "reading": "しみん",
      "meaning": "warga negara"
    },
    {
      "word": "民間",
      "reading": "みんかん",
      "meaning": "swasta, sipil"
    }
  ],
  "idioms": [],
  "lessons": [
    {
      "japanese": "英国民は無口な国民だ。",
      "reading": null,
      "indonesian": "The English are a taciturn people.",
      "lessonInfo": {
        "level": "intermediate"
      }
    },
    {
      "japanese": "それこそ、英国民が女王に期待していることなのです。",
      "reading": null,
      "indonesian": "That is what the British people expect of their Queen.",
      "lessonInfo": {
        "level": "intermediate"
      }
    }
  ]
}