{
  "definition": {
    "word": "待合室",
    "reading": "まちあいしつ",
    "romaji": "machiaishitsu",
    "jlpt": "N2",
    "frequency": 5000,
    "entries": [
      {
        "pos": [
          "noun (common) (futsuumeishi)"
        ],
        "meanings": [
          "ruang tunggu"
        ]
      }
    ]
  },
  "related": [
    {
      "word": "集合",
      "reading": "しゅうごう",
      "meaning": "pertemuan, perkumpulan"
    },
    {
      "word": "合理",
      "reading": "ごうり",
      "meaning": "rasional"
    },
    {
      "word": "混合",
      "reading": "こんごう",
      "meaning": "pencampuran, campuran"
    },
    {
      "word": "温室",
      "reading": "おんしつ",
      "meaning": "rumah kaca"
    },
    {
      "word": "連合",
      "reading": "れんごう",
      "meaning": "persatuan, aliansi"
    },
    {
      "word": "問い合わせ",
      "reading": "といあわせ",
      "meaning": "pertanyaan"
    },
    {
      "word": "合同",
      "reading": "ごうどう",
      "meaning": "kombinasi, penggabungan"
    },
    {
      "word": "応対",
      "reading": "おうたい",
      "meaning": "menerima, menangani"
    },
    {
      "word": "合流",
      "reading": "ごうりゅう",
      "meaning": "pertemuan, penggabungan, bergabung"
    },
    {
      "word": "招待",
      "reading": "しょうたい",
      "meaning": "undangan"
    },
    {
      "word": "合格",
      "reading": "ごうかく",
      "meaning": "sukses, lulus (misalnya, ujian)"
    },
    {
      "word": "待遇",
      "reading": "たいぐう",
      "meaning": "perawatan, penerimaan"
    },
    {
      "word": "付き合い",
      "reading": "つきあい",
      "meaning": "sosialisasi; persahabatan; pergaulan"
    },
    {
      "word": "複合",
      "reading": "ふくごう",
      "meaning": "komposit, kompleks"
    }
  ],
  "idioms": [],
  "lessons": [
    {
      "japanese": "待合室で少々お待ちください。",
      "reading": null,
      "indonesian": "Wait in the waiting room.",
      "lessonInfo": {
        "level": "intermediate"
      }
    }
  ]
}