{
  "definition": {
    "word": "股",
    "reading": "また",
    "romaji": "mata",
    "jlpt": "N3",
    "frequency": 12250,
    "entries": [
      {
        "pos": [
          "noun (common) (futsuumeishi)"
        ],
        "meanings": [
          "paha",
          "tulang paha"
        ]
      },
      {
        "pos": [
          "noun (common) (futsuumeishi)"
        ],
        "meanings": [
          "fork (in a tree, road, river, etc.)",
          "tines (of a fork)"
        ]
      }
    ]
  },
  "related": [],
  "idioms": [
    {
      "word": "二股膏薬",
      "reading": "ふたまたこうやく",
      "meaning": "double-dealer",
      "type": "yojijukugo"
    },
    {
      "word": "内股膏薬",
      "reading": "うちまたこうやく",
      "meaning": "double-dealer",
      "type": "yojijukugo"
    },
    {
      "word": "股にかける",
      "reading": "またにかける",
      "meaning": "to travel all over",
      "type": "idiom"
    },
    {
      "word": "二股をかける",
      "reading": "ふたまたをかける",
      "meaning": "to cheat (in a romantic relationship)",
      "type": "idiom"
    },
    {
      "word": "股を開く",
      "reading": "またをひらく",
      "meaning": "to spread one's legs",
      "type": "idiom"
    },
    {
      "word": "欲の熊鷹股裂く",
      "reading": "よくのくまたかまたさく",
      "meaning": "avarice brings doom upon oneself",
      "type": "proverb"
    }
  ],
  "lessons": []
}