{
  "definition": {
    "word": "華やか",
    "reading": "はなやか",
    "romaji": "hanayaka",
    "jlpt": "N1",
    "frequency": 4250,
    "entries": [
      {
        "pos": [
          "adjectival nouns or quasi-adjectives (keiyodoshi)"
        ],
        "meanings": [
          "cemerlang",
          "cantik",
          "berbunga-bunga"
        ]
      },
      {
        "pos": [
          "adjectival nouns or quasi-adjectives (keiyodoshi)"
        ],
        "meanings": [
          "prosperous",
          "flourishing",
          "thriving"
        ]
      }
    ]
  },
  "related": [
    {
      "word": "豪華",
      "reading": "ごうか",
      "meaning": "mewah, cantik, megah"
    },
    {
      "word": "華々しい",
      "reading": "はなばなしい",
      "meaning": "cemerlang, megah, spektakuler"
    }
  ],
  "idioms": [],
  "lessons": [
    {
      "japanese": "ショービジネスというのは本当に華やかだ。",
      "reading": null,
      "indonesian": "Show business is really glamorous.",
      "lessonInfo": {
        "level": "upper-intermediate"
      }
    },
    {
      "japanese": "アカデミー授賞式は、ハリウッド最大の華やかな催しだ。",
      "reading": null,
      "indonesian": "The Oscar ceremonies are Hollywood's biggest extravaganza.",
      "lessonInfo": {
        "level": "upper-intermediate"
      }
    },
    {
      "japanese": "アカデミー授賞式は、ハリウッド最大の華やかな催しだ。",
      "reading": null,
      "indonesian": "The Oscar ceremonies are Hollywood's biggest extravaganza.",
      "lessonInfo": {
        "level": "upper-intermediate"
      }
    },
    {
      "japanese": "ショービジネスというのは本当に華やかだ。",
      "reading": null,
      "indonesian": "Show business is really glamorous.",
      "lessonInfo": {
        "level": "upper-intermediate"
      }
    },
    {
      "japanese": "華やかだこと。",
      "reading": null,
      "indonesian": "It's gorgeous.",
      "lessonInfo": {
        "level": "intermediate"
      }
    },
    {
      "japanese": "彼女はとても華やかだね。",
      "reading": null,
      "indonesian": "She's quite gorgeous.",
      "lessonInfo": {
        "level": "intermediate"
      }
    },
    {
      "japanese": "ものすごく華やかだったわよ。",
      "reading": null,
      "indonesian": "She was absolutely gorgeous.",
      "lessonInfo": {
        "level": "intermediate"
      }
    },
    {
      "japanese": "彼女はとても華やかだね。",
      "reading": null,
      "indonesian": "She's quite gorgeous.",
      "lessonInfo": {
        "level": "intermediate"
      }
    },
    {
      "japanese": "華やかだこと。",
      "reading": null,
      "indonesian": "It's gorgeous.",
      "lessonInfo": {
        "level": "intermediate"
      }
    },
    {
      "japanese": "ものすごく華やかだったわよ。",
      "reading": null,
      "indonesian": "She was absolutely gorgeous.",
      "lessonInfo": {
        "level": "intermediate"
      }
    }
  ]
}