{
  "definition": {
    "word": "課税",
    "reading": "かぜい",
    "romaji": "kazei",
    "jlpt": "N2",
    "frequency": 1250,
    "entries": [
      {
        "pos": [
          "noun (common) (futsuumeishi)",
          "noun or participle which takes the aux. verb suru",
          "intransitive verb"
        ],
        "meanings": [
          "perpajakan"
        ]
      }
    ]
  },
  "related": [
    {
      "word": "税関",
      "reading": "ぜいかん",
      "meaning": "bea cukai"
    },
    {
      "word": "免税",
      "reading": "めんぜい",
      "meaning": "pembebasan pajak"
    },
    {
      "word": "日課",
      "reading": "にっか",
      "meaning": "pekerjaan sehari-hari, rutinitas harian"
    },
    {
      "word": "課題",
      "reading": "かだい",
      "meaning": "subjek, tema, tugas"
    },
    {
      "word": "課長",
      "reading": "かちょう",
      "meaning": "manajer bagian"
    },
    {
      "word": "関税",
      "reading": "かんぜい",
      "meaning": "bea cukai, pajak, tarif"
    },
    {
      "word": "税金",
      "reading": "ぜいきん",
      "meaning": "pajak, bea"
    },
    {
      "word": "課",
      "reading": "か",
      "meaning": "departemen, divisi"
    }
  ],
  "idioms": [],
  "lessons": [
    {
      "japanese": "課税問題で意見が分かれている。",
      "reading": null,
      "indonesian": "Opinions are divided on the issue of taxes.",
      "lessonInfo": {
        "level": "intermediate"
      }
    },
    {
      "japanese": "課税品をお持ちですか。",
      "reading": null,
      "indonesian": "Do you have anything to declare?",
      "lessonInfo": {
        "level": "intermediate"
      }
    },
    {
      "japanese": "輸入品は高い課税対象だ。",
      "reading": null,
      "indonesian": "Import goods are subject to high taxes.",
      "lessonInfo": {
        "level": "intermediate"
      }
    },
    {
      "japanese": "課税問題で意見が分かれている。",
      "reading": null,
      "indonesian": "Opinions are divided on the issue of taxes.",
      "lessonInfo": {
        "level": "intermediate"
      }
    },
    {
      "japanese": "課税品をお持ちですか。",
      "reading": null,
      "indonesian": "Do you have anything to declare?",
      "lessonInfo": {
        "level": "intermediate"
      }
    },
    {
      "japanese": "課税は所得に応じて行われます。",
      "reading": null,
      "indonesian": "Taxation is based on income.",
      "lessonInfo": {
        "level": "intermediate"
      }
    },
    {
      "japanese": "輸入品は高い課税対象だ。",
      "reading": null,
      "indonesian": "Import goods are subject to high taxes.",
      "lessonInfo": {
        "level": "intermediate"
      }
    },
    {
      "japanese": "５万円未満の場合は、非課税になります。",
      "reading": null,
      "indonesian": "It's tax-free in the case it's below ¥50,000.",
      "lessonInfo": {
        "level": "upper-intermediate"
      }
    },
    {
      "japanese": "５万円未満の場合は、非課税になります。",
      "reading": null,
      "indonesian": "It's tax-exempt in the case it's below ¥50,000.",
      "lessonInfo": {
        "level": "upper-intermediate"
      }
    },
    {
      "japanese": "５万円未満の場合は、非課税になります。",
      "reading": null,
      "indonesian": "It's tax-free in the case it's below 50,000 yen.",
      "lessonInfo": {
        "level": "upper-intermediate"
      }
    },
    {
      "japanese": "５万円未満の場合は、非課税になります。",
      "reading": null,
      "indonesian": "It's tax-exempt in the case it's below 50,000 yen.",
      "lessonInfo": {
        "level": "upper-intermediate"
      }
    }
  ]
}